<annotation>
	<folder></folder>
	<filename>-6-_jpg.rf.8e9fa2ced43c2b3f66f1359426b478cc.jpg</filename>
	<path>-6-_jpg.rf.8e9fa2ced43c2b3f66f1359426b478cc.jpg</path>
	<source>
		<database>roboflow.com</database>
	</source>
	<size>
		<width>640</width>
		<height>640</height>
		<depth>3</depth>
	</size>
	<segmented>0</segmented>
	<object>
		<name>bazooka</name>
		<pose>Unspecified</pose>
		<truncated>0</truncated>
		<difficult>0</difficult>
		<occluded>0</occluded>
		<bndbox>
			<xmin>60</xmin>
			<xmax>483</xmax>
			<ymin>123</ymin>
			<ymax>526</ymax>
		</bndbox>
	</object>
	<metadata>
	</metadata>
</annotation>
