<annotation>
	<folder></folder>
	<filename>armas_480_jpg.rf.b4a80e62cba8bf8a09feca8b8975ea62.jpg</filename>
	<path>armas_480_jpg.rf.b4a80e62cba8bf8a09feca8b8975ea62.jpg</path>
	<source>
		<database>roboflow.com</database>
	</source>
	<size>
		<width>640</width>
		<height>640</height>
		<depth>3</depth>
	</size>
	<segmented>0</segmented>
	<object>
		<name>pistol</name>
		<pose>Unspecified</pose>
		<truncated>0</truncated>
		<difficult>0</difficult>
		<occluded>0</occluded>
		<bndbox>
			<xmin>206</xmin>
			<xmax>366</xmax>
			<ymin>275</ymin>
			<ymax>570</ymax>
		</bndbox>
	</object>
</annotation>
