<annotation>
	<folder></folder>
	<filename>bazooka_152_jpg.rf.abb14c36b17cb36a524ed086f69667f0.jpg</filename>
	<path>bazooka_152_jpg.rf.abb14c36b17cb36a524ed086f69667f0.jpg</path>
	<source>
		<database>roboflow.com</database>
	</source>
	<size>
		<width>640</width>
		<height>640</height>
		<depth>3</depth>
	</size>
	<segmented>0</segmented>
	<object>
		<name>bazooka</name>
		<pose>Unspecified</pose>
		<truncated>0</truncated>
		<difficult>0</difficult>
		<occluded>0</occluded>
		<bndbox>
			<xmin>17</xmin>
			<xmax>620</xmax>
			<ymin>45</ymin>
			<ymax>587</ymax>
		</bndbox>
	</object>
	<metadata>
	</metadata>
</annotation>
