<annotation>
	<folder></folder>
	<filename>grenade_1303_jpg.rf.fbd96f719ccc70291cba3dfdf7ca64cd.jpg</filename>
	<path>grenade_1303_jpg.rf.fbd96f719ccc70291cba3dfdf7ca64cd.jpg</path>
	<source>
		<database>roboflow.com</database>
	</source>
	<size>
		<width>640</width>
		<height>640</height>
		<depth>3</depth>
	</size>
	<segmented>0</segmented>
	<object>
		<name>grenade</name>
		<pose>Unspecified</pose>
		<truncated>0</truncated>
		<difficult>0</difficult>
		<occluded>0</occluded>
		<bndbox>
			<xmin>120</xmin>
			<xmax>531</xmax>
			<ymin>60</ymin>
			<ymax>535</ymax>
		</bndbox>
	</object>
</annotation>
