<annotation>
	<folder></folder>
	<filename>grenade_0304_jpg.rf.dddd88a5de384fe8ee51f79865d8eee7.jpg</filename>
	<path>grenade_0304_jpg.rf.dddd88a5de384fe8ee51f79865d8eee7.jpg</path>
	<source>
		<database>roboflow.com</database>
	</source>
	<size>
		<width>640</width>
		<height>640</height>
		<depth>3</depth>
	</size>
	<segmented>0</segmented>
	<object>
		<name>grenade</name>
		<pose>Unspecified</pose>
		<truncated>0</truncated>
		<difficult>0</difficult>
		<occluded>0</occluded>
		<bndbox>
			<xmin>194</xmin>
			<xmax>245</xmax>
			<ymin>128</ymin>
			<ymax>237</ymax>
		</bndbox>
	</object>
	<object>
		<name>grenade</name>
		<pose>Unspecified</pose>
		<truncated>0</truncated>
		<difficult>0</difficult>
		<occluded>0</occluded>
		<bndbox>
			<xmin>177</xmin>
			<xmax>242</xmax>
			<ymin>173</ymin>
			<ymax>277</ymax>
		</bndbox>
	</object>
	<object>
		<name>grenade</name>
		<pose>Unspecified</pose>
		<truncated>0</truncated>
		<difficult>0</difficult>
		<occluded>0</occluded>
		<bndbox>
			<xmin>108</xmin>
			<xmax>168</xmax>
			<ymin>146</ymin>
			<ymax>332</ymax>
		</bndbox>
	</object>
	<object>
		<name>grenade</name>
		<pose>Unspecified</pose>
		<truncated>0</truncated>
		<difficult>0</difficult>
		<occluded>0</occluded>
		<bndbox>
			<xmin>259</xmin>
			<xmax>314</xmax>
			<ymin>173</ymin>
			<ymax>308</ymax>
		</bndbox>
	</object>
	<object>
		<name>grenade</name>
		<pose>Unspecified</pose>
		<truncated>0</truncated>
		<difficult>0</difficult>
		<occluded>0</occluded>
		<bndbox>
			<xmin>265</xmin>
			<xmax>338</xmax>
			<ymin>208</ymin>
			<ymax>381</ymax>
		</bndbox>
	</object>
	<object>
		<name>grenade</name>
		<pose>Unspecified</pose>
		<truncated>0</truncated>
		<difficult>0</difficult>
		<occluded>0</occluded>
		<bndbox>
			<xmin>49</xmin>
			<xmax>130</xmax>
			<ymin>198</ymin>
			<ymax>410</ymax>
		</bndbox>
	</object>
	<object>
		<name>grenade</name>
		<pose>Unspecified</pose>
		<truncated>0</truncated>
		<difficult>0</difficult>
		<occluded>0</occluded>
		<bndbox>
			<xmin>170</xmin>
			<xmax>244</xmax>
			<ymin>234</ymin>
			<ymax>432</ymax>
		</bndbox>
	</object>
	<object>
		<name>grenade</name>
		<pose>Unspecified</pose>
		<truncated>0</truncated>
		<difficult>0</difficult>
		<occluded>0</occluded>
		<bndbox>
			<xmin>329</xmin>
			<xmax>448</xmax>
			<ymin>204</ymin>
			<ymax>573</ymax>
		</bndbox>
	</object>
	<object>
		<name>grenade</name>
		<pose>Unspecified</pose>
		<truncated>0</truncated>
		<difficult>0</difficult>
		<occluded>0</occluded>
		<bndbox>
			<xmin>222</xmin>
			<xmax>329</xmax>
			<ymin>308</ymin>
			<ymax>626</ymax>
		</bndbox>
	</object>
	<object>
		<name>grenade</name>
		<pose>Unspecified</pose>
		<truncated>0</truncated>
		<difficult>0</difficult>
		<occluded>0</occluded>
		<bndbox>
			<xmin>59</xmin>
			<xmax>179</xmax>
			<ymin>308</ymin>
			<ymax>637</ymax>
		</bndbox>
	</object>
	<object>
		<name>grenade</name>
		<pose>Unspecified</pose>
		<truncated>0</truncated>
		<difficult>0</difficult>
		<occluded>0</occluded>
		<bndbox>
			<xmin>471</xmin>
			<xmax>586</xmax>
			<ymin>392</ymin>
			<ymax>596</ymax>
		</bndbox>
	</object>
</annotation>
