<annotation>
	<folder></folder>
	<filename>knife_311_jpg.rf.1480b502017af0476a4c41e55896caa2.jpg</filename>
	<path>knife_311_jpg.rf.1480b502017af0476a4c41e55896caa2.jpg</path>
	<source>
		<database>roboflow.com</database>
	</source>
	<size>
		<width>640</width>
		<height>640</height>
		<depth>3</depth>
	</size>
	<segmented>0</segmented>
	<object>
		<name>knife</name>
		<pose>Unspecified</pose>
		<truncated>0</truncated>
		<difficult>0</difficult>
		<occluded>0</occluded>
		<bndbox>
			<xmin>307</xmin>
			<xmax>346</xmax>
			<ymin>86</ymin>
			<ymax>336</ymax>
		</bndbox>
	</object>
</annotation>
