<annotation>
	<folder></folder>
	<filename>knife_1286_jpg.rf.a7d3bea2a8f30082b543920376816236.jpg</filename>
	<path>knife_1286_jpg.rf.a7d3bea2a8f30082b543920376816236.jpg</path>
	<source>
		<database>roboflow.com</database>
	</source>
	<size>
		<width>640</width>
		<height>640</height>
		<depth>3</depth>
	</size>
	<segmented>0</segmented>
	<object>
		<name>knife</name>
		<pose>Unspecified</pose>
		<truncated>0</truncated>
		<difficult>0</difficult>
		<occluded>0</occluded>
		<bndbox>
			<xmin>323</xmin>
			<xmax>359</xmax>
			<ymin>301</ymin>
			<ymax>347</ymax>
		</bndbox>
	</object>
</annotation>
