<annotation>
	<folder></folder>
	<filename>rifle_2372_jpg.rf.3a572fb2ca54281b7b92903bbd989110.jpg</filename>
	<path>rifle_2372_jpg.rf.3a572fb2ca54281b7b92903bbd989110.jpg</path>
	<source>
		<database>roboflow.com</database>
	</source>
	<size>
		<width>640</width>
		<height>640</height>
		<depth>3</depth>
	</size>
	<segmented>0</segmented>
	<object>
		<name>rifle</name>
		<pose>Unspecified</pose>
		<truncated>0</truncated>
		<difficult>0</difficult>
		<occluded>0</occluded>
		<bndbox>
			<xmin>76</xmin>
			<xmax>491</xmax>
			<ymin>9</ymin>
			<ymax>641</ymax>
		</bndbox>
	</object>
</annotation>
