<annotation>
	<folder></folder>
	<filename>rifle_680_jpg.rf.0403ffe7d26cb8281f0d0cf0f491552b.jpg</filename>
	<path>rifle_680_jpg.rf.0403ffe7d26cb8281f0d0cf0f491552b.jpg</path>
	<source>
		<database>roboflow.com</database>
	</source>
	<size>
		<width>640</width>
		<height>640</height>
		<depth>3</depth>
	</size>
	<segmented>0</segmented>
	<object>
		<name>rifle</name>
		<pose>Unspecified</pose>
		<truncated>0</truncated>
		<difficult>0</difficult>
		<occluded>0</occluded>
		<bndbox>
			<xmin>7</xmin>
			<xmax>641</xmax>
			<ymin>18</ymin>
			<ymax>612</ymax>
		</bndbox>
	</object>
</annotation>
