<annotation>
	<folder></folder>
	<filename>rifle_420_jpg.rf.b42300da32862619e7e65b0a6a5a7b03.jpg</filename>
	<path>rifle_420_jpg.rf.b42300da32862619e7e65b0a6a5a7b03.jpg</path>
	<source>
		<database>roboflow.com</database>
	</source>
	<size>
		<width>640</width>
		<height>640</height>
		<depth>3</depth>
	</size>
	<segmented>0</segmented>
	<object>
		<name>rifle</name>
		<pose>Unspecified</pose>
		<truncated>0</truncated>
		<difficult>0</difficult>
		<occluded>0</occluded>
		<bndbox>
			<xmin>102</xmin>
			<xmax>262</xmax>
			<ymin>448</ymin>
			<ymax>521</ymax>
		</bndbox>
	</object>
</annotation>
