<annotation>
	<folder></folder>
	<filename>rifle_395_jpg.rf.043705dfddf7d7cffcb466771906fd74.jpg</filename>
	<path>rifle_395_jpg.rf.043705dfddf7d7cffcb466771906fd74.jpg</path>
	<source>
		<database>roboflow.com</database>
	</source>
	<size>
		<width>640</width>
		<height>640</height>
		<depth>3</depth>
	</size>
	<segmented>0</segmented>
	<object>
		<name>rifle</name>
		<pose>Unspecified</pose>
		<truncated>0</truncated>
		<difficult>0</difficult>
		<occluded>0</occluded>
		<bndbox>
			<xmin>348</xmin>
			<xmax>594</xmax>
			<ymin>399</ymin>
			<ymax>576</ymax>
		</bndbox>
	</object>
</annotation>
