<annotation>
	<folder></folder>
	<filename>tabanca344_jpg.rf.cdb64b0b2c4cb34470ac7a6ff577ae22.jpg</filename>
	<path>tabanca344_jpg.rf.cdb64b0b2c4cb34470ac7a6ff577ae22.jpg</path>
	<source>
		<database>roboflow.com</database>
	</source>
	<size>
		<width>640</width>
		<height>640</height>
		<depth>3</depth>
	</size>
	<segmented>0</segmented>
	<object>
		<name>pistol</name>
		<pose>Unspecified</pose>
		<truncated>0</truncated>
		<difficult>0</difficult>
		<occluded>0</occluded>
		<bndbox>
			<xmin>100</xmin>
			<xmax>561</xmax>
			<ymin>78</ymin>
			<ymax>494</ymax>
		</bndbox>
	</object>
</annotation>
